[
  {"question": "Can you recommend parking spots twice?", "answer": "SEQ[parking_recommendation; parking_recommendation]"},
  {"question": "Is event booking available?", "answer": "event_booking"},
  {"question": "Is it possible to check for ticket availability or parking recommendations?", "answer": "ONEOF[ticket_availability; parking_recommendation]"},
  {"question": "What is the weather like?", "answer": "weather_checking"},
  {"question": "Tell me about parking recommendations and check the weather.", "answer": "SEQ[parking_recommendation; weather_checking]"},
  {"question": "Should I recommend parking spots or recommend parking spots again?", "answer": "ONEOF[parking_recommendation; parking_recommendation]"},
  {"question": "Should I book an event or book an event again?", "answer": "ONEOF[event_booking; event_booking]"},
  {"question": "Tell me about parking recommendations.", "answer": "parking_recommendation"},
  {"question": "Can I book an event and check for ticket availability?", "answer": "SEQ[event_booking; ticket_availability]"},
  {"question": "Should I book an event or check for ticket availability?", "answer": "ONEOF[event_booking; ticket_availability]"},
  {"question": "Should I recommend parking spots or check for ticket availability?", "answer": "ONEOF[parking_recommendation; ticket_availability]"},
  {"question": "Is ticket availability possible?", "answer": "ticket_availability"},
  {"question": "Check the weather and recommend parking spots.", "answer": "SEQ[weather_checking; parking_recommendation]"},
  {"question": "Check for ticket availability and recommend parking spots.", "answer": "SEQ[ticket_availability; parking_recommendation]"},
  {"question": "Should I check for ticket availability or book an event?", "answer": "ONEOF[ticket_availability; event_booking]"},
  {"question": "Recommend parking spots twice.", "answer": "[parking_recommendation AND parking_recommendation]"},
  {"question": "Should I check the weather or check for ticket availability?", "answer": "ONEOF[weather_checking; ticket_availability]"},
  {"question": "Book an event twice.", "answer": "SEQ[event_booking; event_booking]"},
  {"question": "Check the weather and recommend parking spots together.", "answer": "[weather_checking AND parking_recommendation]"},
  {"question": "Should I check for ticket availability or the weather?", "answer": "ONEOF[ticket_availability; weather_checking]"},
  {"question": "Should I check the weather or recommend parking spots?", "answer": "ONEOF[weather_checking; parking_recommendation]"},
  {"question": "Check the weather and look for ticket availability.", "answer": "SEQ[weather_checking; ticket_availability]"},
  {"question": "Book an event and check the weather.", "answer": "SEQ[event_booking; weather_checking]"},
  {"question": "Check the weather and book an event.", "answer": "SEQ[weather_checking; event_booking]"},
  {"question": "Should I book an event or recommend parking spots?", "answer": "ONEOF[event_booking; parking_recommendation]"},
  {"question": "Should I recommend parking spots or check the weather?", "answer": "ONEOF[parking_recommendation; weather_checking]"},
  {"question": "Book an event and check the weather or recommend parking spots.", "answer": "[event_booking AND [weather_checking OR parking_recommendation]]"},
  {"question": "Check the weather or recommend parking spots?", "answer": "[weather_checking OR parking_recommendation]"},
  {"question": "Should I recommend parking spots and look for ticket availability?", "answer": "SEQ[parking_recommendation; ticket_availability]"},
  {"question": "Look for ticket availability and check the weather or book an event.", "answer": "[ticket_availability AND [weather_checking OR event_booking]]"},
  {"question": "Should I book an event or check the weather?", "answer": "ONEOF[event_booking; weather_checking]"},
  {"question": "Book an event or book an event again?", "answer": "[event_booking OR event_booking]"},
  {"question": "Look for ticket availability or check the weather?", "answer": "[ticket_availability OR weather_checking]"},
  {"question": "Check the weather twice.", "answer": "SEQ[weather_checking; weather_checking]"},
  {"question": "Look for ticket availability and check the weather.", "answer": "SEQ[ticket_availability; weather_checking]"},
  {"question": "Look for ticket availability twice.", "answer": "SEQ[ticket_availability; ticket_availability]"},
  {"question": "Should I check the weather or book an event?", "answer": "ONEOF[weather_checking; event_booking]"},
  {"question": "Should I look for ticket availability or look for ticket availability again?", "answer": "ONEOF[ticket_availability; ticket_availability]"},
  {"question": "Recommend parking spots and book an event.", "answer": "SEQ[parking_recommendation; event_booking]"},
  {"question": "Recommend parking spots or look for ticket availability?", "answer": "[parking_recommendation OR ticket_availability]"},
  {"question": "Is the weather checking happening or is the weather checking happening again?", "answer": "[weather_checking OR weather_checking]"},
  {"question": "Is the weather checking happening twice, and are there ticket availability?", "answer": "[[weather_checking OR weather_checking] AND ticket_availability]"},
  {"question": "Is there event booking or ticket availability?", "answer": "[event_booking OR ticket_availability]"},
  {"question": "Should I check the weather or should I check the weather again?", "answer": "ONEOF[weather_checking; weather_checking]"},
  {"question": "Should I recommend parking spots and book an event?", "answer": "[parking_recommendation AND event_booking]"},
  {"question": "Should I check both the weather and recommend parking spots or look for ticket availability?", "answer": "[[weather_checking AND parking_recommendation] OR ticket_availability]"},
  {"question": "Is there event booking or is there ticket availability and weather checking?", "answer": "[event_booking OR [ticket_availability AND weather_checking]]"},
  {"question": "Should I look for ticket availability and then book an event?", "answer": "SEQ[ticket_availability; event_booking]"},
  {"question": "Should I look for ticket availability and recommend parking spots?", "answer": "[ticket_availability AND parking_recommendation]"},
  {"question": "Should I recommend parking spots or book an event?", "answer": "[parking_recommendation OR event_booking]"},
  {"question": "Is there event booking or is there event booking again and ticket availability?", "answer": "[[event_booking OR event_booking] AND ticket_availability]"},
  {"question": "Book an event and recommend parking spots.", "answer": "SEQ[event_booking; parking_recommendation]"},
  {"question": "Should I recommend parking spots or book an event?", "answer": "ONEOF[parking_recommendation; event_booking]"},
  {"question": "Is there event booking and should I recommend parking spots?", "answer": "[event_booking AND parking_recommendation]"},
  {"question": "Is there event booking and weather checking?", "answer": "[event_booking AND weather_checking]"},
  {"question": "Is there ticket availability and weather checking?", "answer": "[ticket_availability AND weather_checking]"},
  {"question": "Should I check the weather or is there event booking?", "answer": "[weather_checking OR event_booking]"},
  {"question": "Is there event booking and is there event booking again or is there ticket availability?", "answer": "[event_booking AND [event_booking OR ticket_availability]]"},
  {"question": "Is there ticket availability and is there ticket availability again?", "answer": "[ticket_availability AND ticket_availability]"},
  {"question": "Should I recommend parking spots or should I recommend parking spots again?", "answer": "[parking_recommendation OR parking_recommendation]"},
  {"question": "Is there weather checking or is there ticket availability?", "answer": "[weather_checking OR ticket_availability]"},
  {"question": "Is there ticket availability or is there event booking?", "answer": "[ticket_availability OR event_booking]"},
  {"question": "Are there two weather checking occurrences?", "answer": "[weather_checking AND weather_checking]"},
  {"question": "Is there weather checking and is there ticket availability?", "answer": "[weather_checking AND ticket_availability]"},
  {"question": "Is there parking recommendation or is there weather checking?", "answer": "[parking_recommendation OR weather_checking]"},
  {"question": "Is there event booking or is there parking recommendation?", "answer": "[event_booking OR parking_recommendation]"},
  {"question": "Is there parking recommendation and is there ticket availability?", "answer": "[parking_recommendation AND ticket_availability]"},
  {"question": "Is there ticket availability or is there parking recommendation?", "answer": "[ticket_availability OR parking_recommendation]"},
  {"question": "Is there ticket availability or is there ticket availability again?", "answer": "[ticket_availability OR ticket_availability]"},
  {"question": "Is there weather checking and is there event booking?", "answer": "[weather_checking AND event_booking]"},
  {"question": "Is there ticket availability and is there event booking?", "answer": "[ticket_availability AND event_booking]"},
  {"question": "Is there weather checking and is there event booking or is there event booking again?", "answer": "[weather_checking AND [event_booking OR event_booking]]"},
  {"question": "Is there event booking and is there event booking again?", "answer": "[event_booking AND event_booking]"},
  {"question": "Is there event booking or is there weather checking?", "answer": "[event_booking OR weather_checking]"},
  {"question": "Is there ticket availability twice or is there ticket availability?", "answer": "[[ticket_availability AND ticket_availability] OR ticket_availability]"},
  {"question": "Is there parking recommendation and is there weather checking?", "answer": "[parking_recommendation AND weather_checking]"},
  {"question": "Is there ticket availability and is there parking recommendation or is there parking recommendation?", "answer": "[[ticket_availability AND parking_recommendation] OR parking_recommendation]"},
  {"question": "Is there event booking and is there ticket availability?", "answer": "[event_booking AND ticket_availability]"},
  {"question": "Is there event booking or is there event booking and parking recommendation?", "answer": "[event_booking OR [event_booking AND parking_recommendation]]"},
  {"question": "Is there ticket availability and is there parking recommendation or is there weather checking?", "answer": "[ticket_availability AND [parking_recommendation OR weather_checking]]"},
  {"question": "Is there event booking or is there weather checking and event booking again?", "answer": "[event_booking OR [weather_checking AND event_booking]]"},
  {"question": "Is there parking recommendation or is there event booking and weather checking?", "answer": "[parking_recommendation OR [event_booking AND weather_checking]]"},
  {"question": "Is there weather checking and ticket availability or is there parking recommendation?", "answer": "[[weather_checking AND ticket_availability] OR parking_recommendation]"},
  {"question": "Is there weather checking or is there parking recommendation and event booking?", "answer": "[weather_checking OR [parking_recommendation AND event_booking]]"},
  {"question": "Is there event booking or is there weather checking and ticket availability?", "answer": "[event_booking OR [weather_checking AND ticket_availability]]"},
  {"question": "Is there ticket availability and event booking or is there ticket availability again?", "answer": "[[ticket_availability AND event_booking] OR ticket_availability]"},
  {"question": "Is there event booking again or is there weather checking twice?", "answer": "[[event_booking AND event_booking] OR weather_checking]"},
  {"question": "Is there ticket availability and should I check for parking recommendation or book an event?", "answer": "[ticket_availability AND [parking_recommendation OR event_booking]]"},
  {"question": "Is there weather checking and ticket availability or is there event booking?", "answer": "[[weather_checking AND ticket_availability] OR event_booking]"},
  {"question": "Is there weather checking or is there parking recommendation and event booking?", "answer": "[weather_checking OR [ticket_availability AND parking_recommendation]]"},
  {"question": "Is there ticket availability or is there parking recommendation and event booking?", "answer": "[[ticket_availability OR parking_recommendation] AND event_booking]"},
  {"question": "Is there event booking or is there event booking again and parking recommendation?", "answer": "[[event_booking OR event_booking] AND parking_recommendation]"},
  {"question": "Is there parking recommendation and ticket availability or is there event booking?", "answer": "[[parking_recommendation AND ticket_availability] OR event_booking]"},
  {"question": "Is there parking recommendation and should I check the weather or book an event?", "answer": "[parking_recommendation AND [weather_checking OR event_booking]]"},
  {"question": "Is there parking recommendation or is there parking recommendation twice?", "answer": "[parking_recommendation OR [parking_recommendation AND parking_recommendation]]"},
  {"question": "Is there weather checking twice or is there parking recommendation?", "answer": "[[weather_checking AND weather_checking] OR parking_recommendation]"},
  {"question": "Is there weather checking and should I check for ticket availability or ticket availability again?", "answer": "[weather_checking AND [ticket_availability OR ticket_availability]]"},
  {"question": "Is there ticket availability and weather checking or is there event booking?", "answer": "[[ticket_availability AND weather_checking] OR event_booking]"},
  {"question": "Is there event booking or is there weather checking and parking recommendation?", "answer": "[event_booking OR [weather_checking AND parking_recommendation]]"},
  {"question": "Is there event booking or is there parking recommendation and event booking?", "answer": "[[event_booking OR parking_recommendation] AND event_booking]"},
  {"question": "Is there event booking or is there parking recommendation and ticket availability?", "answer": "[event_booking OR [parking_recommendation AND ticket_availability]]"},
  {"question": "Is there weather checking and ticket availability or is there ticket availability again?", "answer": "[[weather_checking AND ticket_availability] OR ticket_availability]"},
  {"question": "Is there weather checking and should I check the weather or should I check the weather again?", "answer": "[weather_checking AND [weather_checking OR weather_checking]]"},
  {"question": "Is there weather checking or is there weather checking and should I check the weather again?", "answer": "[weather_checking OR [weather_checking AND weather_checking]]"},
  {"question": "Is there event booking or is there event booking again and event booking?", "answer": "[[event_booking OR event_booking] AND event_booking]"},
  {"question": "Is there parking recommendation or is there weather checking twice?", "answer": "[parking_recommendation OR [weather_checking AND weather_checking]]"},
  {"question": "Is there event booking and should I recommend parking spots or book an event?", "answer": "[event_booking AND [parking_recommendation OR event_booking]]"},
  {"question": "Is there parking recommendation and should I check the weather or should I recommend parking spots?", "answer": "[parking_recommendation AND [weather_checking OR parking_recommendation]]"},
  {"question": "Is there ticket availability or should I check the weather and event booking?", "answer": "[[ticket_availability OR weather_checking] AND event_booking]"},
  {"question": "Is there parking recommendation and event booking or is there event booking again?", "answer": "[[parking_recommendation AND event_booking] OR event_booking]"},
  {"question": "Is there parking recommendation or is there parking recommendation twice and ticket availability?", "answer": "[[parking_recommendation OR parking_recommendation] AND ticket_availability]"},
  {"question": "Is there ticket availability and should I check for ticket availability or should I check for ticket availability again?", "answer": "[ticket_availability AND [ticket_availability OR ticket_availability]]"},
  {"question": "Is there ticket availability or should I check the weather and event booking?", "answer": "[ticket_availability OR [weather_checking AND event_booking]]"},
  {"question": "Is there weather checking or is there event booking and event booking again?", "answer": "[weather_checking OR [event_booking AND event_booking]]"},
  {"question": "Is there parking recommendation and should I check for event booking or should I check for ticket availability?", "answer": "[parking_recommendation AND [event_booking OR ticket_availability]]"},
  {"question": "Is there ticket availability and should I check for event booking or should I check for ticket availability again?", "answer": "[ticket_availability AND [event_booking OR ticket_availability]]"},
  {"question": "Is there weather checking or is there parking recommendation twice?", "answer": "[weather_checking OR [parking_recommendation AND parking_recommendation]]"},
  {"question": "Is there event booking or is there ticket availability and parking recommendation?", "answer": "[[event_booking OR ticket_availability] AND parking_recommendation]"},
  {"question": "Is there parking recommendation and should I recommend parking spots or should I book an event?", "answer": "[parking_recommendation AND [parking_recommendation OR event_booking]]"},
  {"question": "Is there parking recommendation or is there parking recommendation and event booking?", "answer": "[parking_recommendation OR [parking_recommendation AND event_booking]]"},
  {"question": "Is there parking recommendation or is there weather checking, and is there ticket availability?", "answer": "[[parking_recommendation OR weather_checking] AND ticket_availability]"},
  {"question": "Is there ticket availability and should I check for event booking or should I recommend parking spots?", "answer": "[ticket_availability AND [event_booking OR parking_recommendation]]"},
  {"question": "Is there ticket availability and event booking or is there parking recommendation?", "answer": "[[ticket_availability AND event_booking] OR parking_recommendation]"},
  {"question": "Is there parking recommendation or is there ticket availability and parking recommendation?", "answer": "[parking_recommendation OR [ticket_availability AND parking_recommendation]]"},
  {"question": "Is there weather checking and should I check for ticket availability or recommend parking spots?", "answer": "[weather_checking AND [ticket_availability OR parking_recommendation]]"},
  {"question": "Is there event booking and ticket availability or is there parking recommendation?", "answer": "[[event_booking AND ticket_availability] OR parking_recommendation]"},
  {"question": "Is there event booking or is there weather checking, and is there parking recommendation?", "answer": "[[event_booking OR weather_checking] AND parking_recommendation]"},
  {"question": "Is there weather checking and parking recommendation, or is there weather checking again?", "answer": "[[weather_checking AND parking_recommendation] OR weather_checking]"},
  {"question": "Is there event booking and should I check for ticket availability or should I check for event booking again?", "answer": "[event_booking AND [ticket_availability OR event_booking]]"},
  {"question": "Is there weather checking or is there ticket availability, and is there weather checking?", "answer": "[weather_checking OR [ticket_availability AND weather_checking]]"},
  {"question": "Is there event booking and should I check for weather checking or should I check for ticket availability?", "answer": "[event_booking AND [weather_checking OR ticket_availability]]"},
  {"question": "Is there parking recommendation or parking recommendation twice, and is there weather checking?", "answer": "[[parking_recommendation OR parking_recommendation] AND weather_checking]"},
  {"question": "Is there weather checking or ticket availability, and is there event booking?", "answer": "[[weather_checking OR ticket_availability] AND event_booking]"},
  {"question": "Is there parking recommendation and ticket availability, or is there weather checking?", "answer": "[[parking_recommendation AND ticket_availability] OR weather_checking]"},
  {"question": "Is there parking recommendation and should I check for ticket availability, or should I check the weather?", "answer": "[parking_recommendation AND [ticket_availability OR weather_checking]]"},
  {"question": "Is there event booking or is there parking recommendation, and is there weather checking?", "answer": "[[event_booking OR parking_recommendation] AND weather_checking]"},
  {"question": "Is there ticket availability, or is there ticket availability twice, and is there parking recommendation?", "answer": "[ticket_availability OR [ticket_availability AND parking_recommendation]]"},
  {"question": "Is there event booking or is there event booking and event booking?", "answer": "[[event_booking OR event_booking] AND event_booking]"},
  {"question": "Is there parking recommendation or is there event booking, and is there weather checking?", "answer": "[[parking_recommendation OR event_booking] AND weather_checking]"},
  {"question": "Is there parking recommendation or is there ticket availability, and is there ticket availability?", "answer": "[parking_recommendation OR [ticket_availability AND ticket_availability]]"},
  {"question": "Is there ticket availability or is there ticket availability twice, and is there ticket availability?", "answer": "[ticket_availability OR [ticket_availability AND ticket_availability]]"},
  {"question": "Is there weather checking or is there parking recommendation, and is there parking recommendation?", "answer": "[[weather_checking OR parking_recommendation] AND parking_recommendation]"},
  {"question": "Is there parking recommendation and event booking, or is there weather checking?", "answer": "[[parking_recommendation AND event_booking] OR weather_checking]"},
  {"question": "Is there ticket availability or is there event booking, and is there ticket availability?", "answer": "[[ticket_availability OR event_booking] AND ticket_availability]"},
  {"question": "Is there parking recommendation and should I check for event booking or should I recommend parking spots?", "answer": "[parking_recommendation AND [event_booking OR parking_recommendation]]"},
  {"question": "Is there weather checking and should I check the weather or should I check the weather again?", "answer": "[weather_checking AND [weather_checking OR parking_recommendation]]"},
  {"question": "Is there parking recommendation twice, or is there ticket availability?", "answer": "[[parking_recommendation AND parking_recommendation] OR ticket_availability]"},
  {"question": "Is there event booking and weather checking, or is there weather checking?", "answer": "[[event_booking AND weather_checking] OR weather_checking]"},
  {"question": "Is there event booking or should I check for ticket availability and event booking?", "answer": "[event_booking OR [ticket_availability AND event_booking]]"},
  {"question": "Is there ticket availability and should I check for weather checking or should I check the weather again?", "answer": "[[ticket_availability AND weather_checking] OR weather_checking]"},
  {"question": "Is there ticket availability and parking recommendation, or is there event booking?", "answer": "[[ticket_availability AND parking_recommendation] OR event_booking]"},
  {"question": "Is there weather checking or should I check for ticket availability, and is there ticket availability?", "answer": "[[weather_checking OR ticket_availability] AND ticket_availability]"},
  {"question": "Is there weather checking or is there event booking, and is there weather checking?", "answer": "[[weather_checking OR event_booking] AND weather_checking]"},
  {"question": "Is there weather checking and parking recommendation, or is there parking recommendation?", "answer": "[[weather_checking AND parking_recommendation] OR parking_recommendation]"},
  {"question": "Is there parking recommendation or should I check for ticket availability and event booking?", "answer": "[parking_recommendation OR [ticket_availability AND event_booking]]"},
  {"question": "Is there weather checking and should I check for event booking or should I recommend parking spots?", "answer": "[weather_checking AND [event_booking OR parking_recommendation]]"},
  {"question": "Is there ticket availability or is there parking recommendation twice?", "answer": "[ticket_availability OR [parking_recommendation AND parking_recommendation]]"},
  {"question": "Is there ticket availability or should I check for event booking and event booking?", "answer": "[[ticket_availability OR event_booking] AND event_booking]"},
  {"question": "Is there weather checking or should I check for event booking and parking recommendation?", "answer": "[[weather_checking OR event_booking] AND parking_recommendation]"},
  {"question": "Is there parking recommendation and should I check for weather checking or should I check for ticket availability?", "answer": "[parking_recommendation AND [weather_checking OR ticket_availability]]"},
  {"question": "Is there weather checking or should I check for event booking and weather checking?", "answer": "[weather_checking OR [event_booking AND weather_checking]]"},
  {"question": "Is there parking recommendation and should I recommend parking spots, or should I check for ticket availability?", "answer": "[parking_recommendation AND [parking_recommendation OR ticket_availability]]"},
  {"question": "Is there ticket availability and should I check for event booking or should I check the weather?", "answer": "[ticket_availability AND [event_booking OR weather_checking]]"},
  {"question": "Is there weather checking and should I check the weather or should I check for ticket availability?", "answer": "[weather_checking AND [weather_checking OR ticket_availability]]"},
  {"question": "Is there weather checking or should I check for event booking and should I check for weather checking again?", "answer": "[[weather_checking OR event_booking] AND event_booking]"},
  {"question": "Is there ticket availability or should I check for weather checking and should I check the weather again?", "answer": "[[ticket_availability OR weather_checking] AND weather_checking]"},
  {"question": "Is there weather checking and should I check for event booking or should I check the weather again?", "answer": "[weather_checking AND [event_booking OR weather_checking]]"},
  {"question": "Is there parking recommendation or should I check for ticket availability and should I check for ticket availability again?", "answer": "[[parking_recommendation OR ticket_availability] AND ticket_availability]"},
  {"question": "Is there ticket availability or should I check the weather and should I check the weather again?", "answer": "[ticket_availability OR [weather_checking AND weather_checking]]"},
  {"question": "Is there ticket availability and should I check for event booking or should I check for event booking again?", "answer": "[ticket_availability AND [event_booking OR event_booking]]"},
  {"question": "Is there weather checking and should I check the weather twice, or should I check for event booking?", "answer": "[[weather_checking AND weather_checking] OR event_booking]"},
  {"question": "Is there parking recommendation and should I check for ticket availability, or should I check for ticket availability again?", "answer": "[[parking_recommendation AND ticket_availability] OR ticket_availability]"},
  {"question": "Is there ticket availability or should I check for event booking and should I check the weather?", "answer": "[[ticket_availability OR event_booking] AND weather_checking]"},
  {"question": "Is there weather checking or should I check the weather twice, and is there weather checking?", "answer": "[[weather_checking OR weather_checking] AND weather_checking]"},
  {"question": "Is there ticket availability and should I check for parking recommendation or should I check for parking recommendation again?", "answer": "[ticket_availability AND [parking_recommendation OR parking_recommendation]]"},
  {"question": "Is there parking recommendation and should I check for weather checking or should I check the weather twice?", "answer": "[parking_recommendation AND [weather_checking OR weather_checking]]"},
  {"question": "Is there parking recommendation and should I check for event booking or should I check the weather?", "answer": "[parking_recommendation AND [event_booking OR weather_checking]]"},
  {"question": "Is there parking recommendation or should I check for ticket availability and should I check the weather?", "answer": "[parking_recommendation OR [ticket_availability AND weather_checking]]"},
  {"question": "Is there ticket availability and should I check for event booking or should I check the weather?", "answer": "[[ticket_availability AND event_booking] OR weather_checking]"},
  {"question": "Is there ticket availability or is there ticket availability twice, and is there ticket availability?", "answer": "[[ticket_availability OR ticket_availability] AND ticket_availability]"},
  {"question": "Is there ticket availability and should I check for parking recommendation or should I check for ticket availability again?", "answer": "[ticket_availability AND [parking_recommendation OR ticket_availability]]"},
  {"question": "Is there event booking or should I check for weather checking and should I check the weather again?", "answer": "[event_booking OR [weather_checking AND weather_checking]]"},
  {"question": "Is there event booking or should I check for event booking again and should I check for ticket availability?", "answer": "[event_booking OR [event_booking AND ticket_availability]]"},
  {"question": "Is there event booking or should I check for ticket availability and should I check for ticket availability again?", "answer": "[[event_booking OR ticket_availability] AND ticket_availability]"},
  {"question": "Is there ticket availability and should I check for ticket availability or should I check for event booking?", "answer": "[ticket_availability AND [ticket_availability OR event_booking]]"},
  {"question": "Is there parking recommendation or should I check for event booking and should I check for ticket availability?", "answer": "[parking_recommendation OR [event_booking AND ticket_availability]]"},
  {"question": "Is there ticket availability or should I check for event booking and should I check for parking recommendation?", "answer": "[ticket_availability OR [event_booking AND parking_recommendation]]"},
  {"question": "Is there weather checking or should I check the weather and should I check the weather again, and is there parking recommendation?", "answer": "[weather_checking OR [weather_checking AND parking_recommendation]]"},
  {"question": "Is there ticket availability or should I check for event booking and should I check for ticket availability again?", "answer": "[ticket_availability OR [event_booking AND ticket_availability]]"},
  {"question": "Is there event booking or should I check for parking recommendation and should I check for event booking again?", "answer": "[event_booking OR [parking_recommendation AND event_booking]]"},
  {"question": "Is there event booking and parking recommendation, or is there event booking again?", "answer": "[[event_booking AND parking_recommendation] OR event_booking]"},
  {"question": "Is there parking recommendation or should I check for parking recommendation twice and should I check for ticket availability?", "answer": "[parking_recommendation OR [parking_recommendation AND ticket_availability]]"},
  {"question": "Is there ticket availability or should I check for weather checking and should I check for ticket availability again?", "answer": "[[weather_checking AND event_booking] OR event_booking]"},
  {"question": "Is there weather checking and should I check the weather twice, or is there ticket availability?", "answer": "[[weather_checking AND weather_checking] OR ticket_availability]"},
  {"question": "Is there ticket availability or should I check for parking recommendation and should I check for ticket availability again?", "answer": "[ticket_availability OR [parking_recommendation AND ticket_availability]]"},
  {"question": "Is there parking recommendation and should I check for weather checking or should I check for ticket availability again?", "answer": "[[parking_recommendation AND weather_checking] OR ticket_availability]"},
  {"question": "Is there parking recommendation or should I check for weather checking and should I check the weather again, and is there weather checking?", "answer": "[[parking_recommendation OR weather_checking] AND weather_checking]"},
  {"question": "Is there event booking and should I check for weather checking or should I recommend parking spots?", "answer": "[[event_booking AND weather_checking] OR parking_recommendation]"},
  {"question": "Is there ticket availability or should I check for event booking again and should I check for event booking?", "answer": "[ticket_availability OR [event_booking AND event_booking]]"},
  {"question": "Is there weather checking or parking recommendation, and should I check the weather again?", "answer": "[[weather_checking OR parking_recommendation] AND weather_checking]"},
  {"question": "Is there parking recommendation and should I check for ticket availability or should I check for parking recommendation again?", "answer": "[parking_recommendation AND [ticket_availability OR parking_recommendation]]"},
  {"question": "Is there event booking and should I check for ticket availability or should I check for weather checking again?", "answer": "[event_booking AND [ticket_availability OR weather_checking]]"},
  {"question": "Is there parking recommendation or ticket availability, and should I check for event booking?", "answer": "[[parking_recommendation OR ticket_availability] AND event_booking]"},
  {"question": "Is there ticket availability and weather checking, or should I check for ticket availability or parking recommendation?", "answer": "[[ticket_availability AND weather_checking] OR parking_recommendation]"},
  {"question": "Is there event booking or should I check for parking recommendation twice?", "answer": "[event_booking OR [parking_recommendation AND parking_recommendation]]"},
  {"question": "Is there parking recommendation twice, or is there weather checking?", "answer": "[[parking_recommendation AND parking_recommendation] OR weather_checking]"},
  {"question": "Is there weather checking and should I check for ticket availability or should I check for event booking?", "answer": "[weather_checking AND [ticket_availability OR event_booking]]"},
  {"question": "Is there parking recommendation or should I check for weather checking and should I check the weather again?", "answer": "[parking_recommendation OR [weather_checking AND parking_recommendation]]"},
  {"question": "Is there event booking or parking recommendation, and should I check for parking recommendation again?", "answer": "[[event_booking OR parking_recommendation] AND parking_recommendation]"},
  {"question": "Is there event booking or parking recommendation, and should I check for ticket availability?", "answer": "[[event_booking OR parking_recommendation] AND ticket_availability]"},
  {"question": "Is there parking recommendation and weather checking, or should I check for parking recommendation?", "answer": "[[parking_recommendation AND weather_checking] OR parking_recommendation]"},
  {"question": "Is there event booking or weather checking, and should I check the weather again?", "answer": "[[event_booking OR weather_checking] AND weather_checking]"},
  {"question": "Is there weather checking and should I check the weather or should I check for parking recommendation?", "answer": "[weather_checking AND [parking_recommendation OR ticket_availability]]"},
  {"question": "Is there ticket availability and should I check for weather checking or should I check the weather again?", "answer": "[ticket_availability AND [weather_checking OR ticket_availability]]"},
  {"question": "Is there ticket availability and should I check for ticket availability or should I check for weather checking?", "answer": "[ticket_availability AND [ticket_availability OR weather_checking]]"},
  {"question": "Is there ticket availability and should I check for event booking or should I check for event booking again?", "answer": "[[ticket_availability AND event_booking] OR event_booking]"},
  {"question": "Is there event booking and should I check for weather checking or should I check for event booking again?", "answer": "[[event_booking AND weather_checking] OR event_booking]"},
  {"question": "Is there event booking and parking recommendation, or should I check for ticket availability?", "answer": "[[event_booking AND parking_recommendation] OR ticket_availability]"},
  {"question": "Is there event booking and should I check for event booking or should I check for parking recommendation?", "answer": "[event_booking AND [event_booking OR parking_recommendation]]"},
  {"question": "Is there ticket availability or parking recommendation, and should I check for ticket availability again?", "answer": "[[ticket_availability OR parking_recommendation] AND ticket_availability]"},
  {"question": "Is there weather checking or should I check the weather and should I check for ticket availability?", "answer": "[weather_checking OR [weather_checking AND ticket_availability]]"},
  {"question": "Is there weather checking or should I check for parking recommendation and should I check the weather again?", "answer": "[weather_checking OR [parking_recommendation AND weather_checking]]"},
  {"question": "Is there event booking and parking recommendation, or should I check for parking recommendation again?", "answer": "[[event_booking AND parking_recommendation] OR parking_recommendation]"},
  {"question": "Is there event booking twice, or should I check for ticket availability?", "answer": "[[event_booking AND event_booking] OR ticket_availability]"},
  {"question": "Is there ticket availability or parking recommendation, and should I check for weather checking?", "answer": "[[ticket_availability OR parking_recommendation] AND weather_checking]"},
  {"question": "Is there weather checking and should I check the weather or should I check for parking recommendation?", "answer": "[weather_checking AND [parking_recommendation OR weather_checking]]"},
  {"question": "Is there ticket availability or should I check for parking recommendation and should I check for event booking?", "answer": "[ticket_availability OR [parking_recommendation AND event_booking]]"},
  {"question": "Is there ticket availability twice, or should I check for parking recommendation?", "answer": "[[ticket_availability OR ticket_availability] AND parking_recommendation]"},
  {"question": "Is there parking recommendation or should I check for weather checking and should I check the weather again?", "answer": "[parking_recommendation OR [weather_checking AND ticket_availability]]"},
  {"question": "Is there event booking and should I check for ticket availability or should I check for parking recommendation?", "answer": "[event_booking AND [ticket_availability OR parking_recommendation]]"},
  {"question": "Is there event booking and should I check for event booking or should I check for event booking?", "answer": "[event_booking AND [event_booking OR event_booking]]"},
  {"question": "Is there ticket availability and should I check for weather checking or should I check the weather twice?", "answer": "[ticket_availability AND [weather_checking OR weather_checking]]"},
  {"question": "Is there weather checking or should I check for event booking and should I check for ticket availability?", "answer": "[weather_checking OR [event_booking AND ticket_availability]]"},
  {"question": "Is there parking recommendation or should I check for weather checking and should I check for event booking?", "answer": "[parking_recommendation OR [weather_checking AND event_booking]]"},
  {"question": "Is there ticket availability or event booking, and should I check for parking recommendation?", "answer": "[[ticket_availability OR event_booking] AND parking_recommendation]"},
  {"question": "Is there weather checking and should I check for event booking or should I check for ticket availability?", "answer": "[weather_checking AND [event_booking OR ticket_availability]]"},
  {"question": "Is there event booking or should I check for parking recommendation and should I check for weather checking?", "answer": "[event_booking OR [parking_recommendation AND weather_checking]]"},
  {"question": "Is there event booking and ticket availability, or should I check for event booking?", "answer": "[[event_booking AND ticket_availability] OR event_booking]"},
  {"question": "Is there parking recommendation or ticket availability, and should I check for parking recommendation again?", "answer": "[[parking_recommendation OR ticket_availability] AND parking_recommendation]"},
  {"question": "Is there parking recommendation and should I check for parking recommendation or should I check for weather checking?", "answer": "[parking_recommendation AND [parking_recommendation OR weather_checking]]"},
  {"question": "Is there ticket availability and parking recommendation, or should I check for weather checking?", "answer": "[[ticket_availability AND parking_recommendation] OR weather_checking]"},
  {"question": "Is there event booking and weather checking, or should I check for ticket availability?", "answer": "[[event_booking AND weather_checking] OR ticket_availability]"},
  {"question": "Is there event booking and ticket availability, or should I check for ticket availability?", "answer": "[[event_booking AND ticket_availability] OR ticket_availability]"},
  {"question": "Is there parking recommendation and weather checking, or should I check for event booking?", "answer": "[[parking_recommendation AND weather_checking] OR event_booking]"},
  {"question": "Is there weather checking or ticket availability, and should I check for parking recommendation?", "answer": "[[weather_checking OR ticket_availability] AND parking_recommendation]"},
  {"question": "Is there weather checking or should I check the weather twice, and should I check for parking recommendation?", "answer": "[[weather_checking OR weather_checking] AND parking_recommendation]"},
  {"question": "Is there event booking or should I check for ticket availability and parking recommendation?", "answer": "[event_booking OR [ticket_availability AND parking_recommendation]]"},
  {"question": "Is there parking recommendation or weather checking, and should I check for event booking?", "answer": "[[parking_recommendation OR weather_checking] AND event_booking]"},
  {"question": "Is there parking recommendation twice, or event booking?", "answer": "[[parking_recommendation OR parking_recommendation] AND event_booking]"},
  {"question": "Is there event booking and should I check for event booking or should I check for weather checking?", "answer": "[event_booking AND [event_booking OR weather_checking]]"},
  {"question": "Is there ticket availability or should I check for parking recommendation and should I check for weather checking?", "answer": "[ticket_availability OR [parking_recommendation AND weather_checking]]"},
  {"question": "Is there ticket availability twice, or should I check for event booking?", "answer": "[[ticket_availability OR ticket_availability] AND event_booking]"},
  {"question": "Is there weather checking and ticket availability, or should I check the weather or should I check for weather checking?", "answer": "[[weather_checking AND ticket_availability] OR weather_checking]"},
  {"question": "Is there ticket availability or should I check for event booking and weather checking?", "answer": "[ticket_availability OR [event_booking AND weather_checking]]"},
  {"question": "Is there event booking or ticket availability, and should I check for weather checking?", "answer": "[[event_booking OR ticket_availability] AND weather_checking]"},
  {"question": "Is there weather checking or event booking, and should I check for ticket availability?", "answer": "[[weather_checking OR event_booking] AND ticket_availability]"},
  {"question": "Is there event booking and ticket availability, or should I check for weather checking?", "answer": "[[event_booking AND ticket_availability] OR weather_checking]"},
  {"question": "Is there ticket availability or should I check for ticket availability and weather checking?", "answer": "[ticket_availability OR [ticket_availability AND weather_checking]]"},
  {"question": "Is there weather checking and event booking, or should I check the weather again?", "answer": "[[weather_checking AND event_booking] OR weather_checking]"},
  {"question": "Is there event booking or weather checking, and should I check for event booking?", "answer": "[[event_booking OR weather_checking] AND event_booking]"},
  {"question": "Is there ticket availability and should I check for ticket availability or should I check for parking recommendation?", "answer": "[ticket_availability AND [ticket_availability OR parking_recommendation]]"},
  {"question": "Is there weather checking or parking recommendation, and should I check for ticket availability?", "answer": "[[weather_checking OR parking_recommendation] AND ticket_availability]"},
  {"question": "Is there weather checking and parking recommendation, or should I check for event booking?", "answer": "[[weather_checking AND parking_recommendation] OR event_booking]"},
  {"question": "Is there weather checking and should I check the weather or should I check for event booking?", "answer": "[weather_checking AND [weather_checking OR event_booking]]"},
  {"question": "Is there ticket availability twice, or should I check the weather?", "answer": "[[ticket_availability AND ticket_availability] OR weather_checking]"},
  {"question": "Is there parking recommendation and should I check for ticket availability or event booking?", "answer": "[parking_recommendation AND [ticket_availability OR event_booking]]"},
  {"question": "Is there ticket availability and parking recommendation, or should I check for ticket availability?", "answer": "[[ticket_availability AND parking_recommendation] OR ticket_availability]"},
  {"question": "Is there parking recommendation and weather checking, or should I check the weather again?", "answer": "[[parking_recommendation AND weather_checking] OR weather_checking]"},
  {"question": "Is there parking recommendation or event booking, and should I check for event booking?", "answer": "[[parking_recommendation OR event_booking] AND event_booking]"},
  {"question": "Is there parking recommendation and event booking, or should I check for ticket availability?", "answer": "[[parking_recommendation AND event_booking] OR ticket_availability]"},
  {"question": "Is there weather checking or event booking, and should I check for parking recommendation?", "answer": "[weather_checking OR [event_booking AND parking_recommendation]]"},
  {"question": "Is there ticket availability and should I check for weather checking or parking recommendation?", "answer": "[ticket_availability AND [weather_checking OR parking_recommendation]]"},
  {"question": "Is there event booking twice, and should I check for weather checking?", "answer": "[[event_booking OR event_booking] AND weather_checking]"},
  {"question": "Is there weather checking or should I check the weather and should I check for ticket availability?", "answer": "[weather_checking OR [ticket_availability AND event_booking]]"},
  {"question": "Is there parking recommendation twice, or should I check for parking recommendation?", "answer": "[[parking_recommendation AND parking_recommendation] OR parking_recommendation]"},
  {"question": "Is there parking recommendation or event booking, and should I check for ticket availability?", "answer": "[[parking_recommendation OR event_booking] AND ticket_availability]"},
  {"question": "Is there parking recommendation and event booking, or should I check for parking recommendation?", "answer": "[[parking_recommendation AND event_booking] OR parking_recommendation]"},
  {"question": "Is there parking recommendation or should I check for parking recommendation and should I check for weather checking?", "answer": "[parking_recommendation OR [parking_recommendation AND weather_checking]]"},
  {"question": "Is there event booking and should I check for parking recommendation or weather checking?", "answer": "[event_booking AND [parking_recommendation OR weather_checking]]"},
  {"question": "Is there weather checking or ticket availability, and should I check the weather?", "answer": "[[weather_checking OR ticket_availability] AND weather_checking]"},
  {"question": "Is there event booking and should I check for ticket availability or should I check for ticket availability?", "answer": "[event_booking AND [ticket_availability OR ticket_availability]]"},
  {"question": "Is there parking recommendation and should I check for ticket availability or should I check for ticket availability?", "answer": "[parking_recommendation AND [ticket_availability OR ticket_availability]]"},
  {"question": "Is there event booking and parking recommendation, or should I check for weather checking?", "answer": "[[event_booking AND parking_recommendation] OR weather_checking]"},
  {"question": "Is there weather checking or parking recommendation, and should I check for event booking?", "answer": "[[weather_checking OR parking_recommendation] AND event_booking]"},
  {"question": "Is there ticket availability or should I check for weather checking and parking recommendation?", "answer": "[ticket_availability OR [weather_checking AND parking_recommendation]]"},
  {"question": "Is there parking recommendation twice, or should I check for parking recommendation?", "answer": "[[parking_recommendation OR parking_recommendation] AND parking_recommendation]"},
  {"question": "Is there weather checking and should I check the weather or should I check for parking recommendation?", "answer": "[weather_checking AND [parking_recommendation OR parking_recommendation]]"},
  {"question": "Is there ticket availability or parking recommendation, and should I check for parking recommendation?", "answer": "[[ticket_availability OR parking_recommendation] AND parking_recommendation]"},
  {"question": "Is there parking recommendation or ticket availability, and should I check for weather checking?", "answer": "[[parking_recommendation OR ticket_availability] AND weather_checking]"},
  {"question": "Is there ticket availability twice, or should I check for parking recommendation?", "answer": "[[ticket_availability AND ticket_availability] OR parking_recommendation]"},
  {"question": "Is there parking recommendation or event booking, and should I check for parking recommendation?", "answer": "[[parking_recommendation OR event_booking] AND parking_recommendation]"},
  {"question": "Is there event booking twice, or should I check for event booking?", "answer": "[[event_booking AND event_booking] OR event_booking]"},
  {"question": "Is there ticket availability or should I check for ticket availability and event booking?", "answer": "[ticket_availability OR [ticket_availability AND event_booking]]"},
  {"question": "Is there event booking and should I check for parking recommendation or parking recommendation?", "answer": "[event_booking AND [parking_recommendation OR parking_recommendation]]"},
  {"question": "Is there ticket availability and weather checking, or should I check for ticket availability?", "answer": "[[ticket_availability AND weather_checking] OR ticket_availability]"},



  {
    "question": "Can you suggest parking locations two times?",
    "answer": "SEQ[parking_recommendation; parking_recommendation]"
  },
  {
    "question": "Is there availability for booking events?",
    "answer": "event_booking"
  },
  {
    "question": "Is it feasible to inquire about ticket availability or receive parking recommendations?",
    "answer": "ONEOF[ticket_availability; parking_recommendation]"
  },
  {
    "question": "What's the current weather forecast?",
    "answer": "weather_checking"
  },
  {
    "question": "Inform me about recommended parking areas and provide a weather update.",
    "answer": "SEQ[parking_recommendation; weather_checking]"
  },
  {
    "question": "Should I advise on parking spots or suggest them again?",
    "answer": "ONEOF[parking_recommendation; parking_recommendation]"
  },
  {
    "question": "Should I make a booking for an event or do it again?",
    "answer": "ONEOF[event_booking; event_booking]"
  },
  {
    "question": "Tell me about recommended parking areas.",
    "answer": "parking_recommendation"
  },
  {
    "question": "Can I reserve an event and check for ticket availability?",
    "answer": "SEQ[event_booking; ticket_availability]"
  },
  {
    "question": "Should I reserve an event or check for ticket availability?",
    "answer": "ONEOF[event_booking; ticket_availability]"
  },
  {
    "question": "Should I suggest parking spots or check for ticket availability?",
    "answer": "ONEOF[parking_recommendation; ticket_availability]"
  },
  {
    "question": "Is ticket availability possible?",
    "answer": "ticket_availability"
  },
  {
    "question": "Provide a weather update and suggest parking spots.",
    "answer": "SEQ[weather_checking; parking_recommendation]"
  },
  {
    "question": "Check for ticket availability and recommend parking spots.",
    "answer": "SEQ[ticket_availability; parking_recommendation]"
  },
  {
    "question": "Should I check for ticket availability or book an event?",
    "answer": "ONEOF[ticket_availability; event_booking]"
  },
  {
    "question": "Recommend parking spots twice.",
    "answer": "[parking_recommendation AND parking_recommendation]"
  },
  {
    "question": "Should I check the weather or check for ticket availability?",
    "answer": "ONEOF[weather_checking; ticket_availability]"
  },
  {
    "question": "Book an event twice.",
    "answer": "SEQ[event_booking; event_booking]"
  },
  {
    "question": "Check the weather and suggest parking spots together.",
    "answer": "[weather_checking AND parking_recommendation]"
  }
  {
    "question": "Should I check for ticket availability or the weather?",
    "answer": "ONEOF[ticket_availability; weather_checking]"
  },
  {
    "question": "Should I check the weather or recommend parking spots?",
    "answer": "ONEOF[weather_checking; parking_recommendation]"
  },
  {
    "question": "Check the weather and look for ticket availability.",
    "answer": "SEQ[weather_checking; ticket_availability]"
  },
  {
    "question": "Book an event and check the weather.",
    "answer": "SEQ[event_booking; weather_checking]"
  },
  {
    "question": "Check the weather and book an event.",
    "answer": "SEQ[weather_checking; event_booking]"
  },
  {
    "question": "Should I book an event or recommend parking spots?",
    "answer": "ONEOF[event_booking; parking_recommendation]"
  },
  {
    "question": "Should I recommend parking spots or check the weather?",
    "answer": "ONEOF[parking_recommendation; weather_checking]"
  },
  {
    "question": "Book an event and check the weather or recommend parking spots.",
    "answer": "[event_booking AND [weather_checking OR parking_recommendation]]"
  },
  {
    "question": "Check the weather or recommend parking spots?",
    "answer": "[weather_checking OR parking_recommendation]"
  },
  {
    "question": "Should I recommend parking spots and look for ticket availability?",
    "answer": "SEQ[parking_recommendation; ticket_availability]"
  },
  {
    "question": "Look for ticket availability and check the weather or book an event.",
    "answer": "[ticket_availability AND [weather_checking OR event_booking]]"
  },
  {
    "question": "Should I book an event or check the weather?",
    "answer": "ONEOF[event_booking; weather_checking]"
  },
  {
    "question": "Book an event or book an event again?",
    "answer": "[event_booking OR event_booking]"
  },
  {
    "question": "Look for ticket availability or check the weather?",
    "answer": "[ticket_availability OR weather_checking]"
  },
  {
    "question": "Check the weather twice.",
    "answer": "SEQ[weather_checking; weather_checking]"
  },
  {
    "question": "Look for ticket availability and check the weather.",
    "answer": "SEQ[ticket_availability; weather_checking]"
  },
  {
    "question": "Look for ticket availability twice.",
    "answer": "SEQ[ticket_availability; ticket_availability]"
  },
  {
    "question": "Should I check the weather or book an event?",
    "answer": "ONEOF[weather_checking; event_booking]"
  },
  {
    "question": "Should I look for ticket availability or look for ticket availability again?",
    "answer": "ONEOF[ticket_availability; ticket_availability]"
  },
  {
    "question": "Recommend parking spots and book an event.",
    "answer": "SEQ[parking_recommendation; event_booking]"
  }

  {
    "question": "Recommend parking spots or look for ticket availability?",
    "answer": "[parking_recommendation OR ticket_availability]"
  },
  {
    "question": "Is the weather checking happening or is the weather checking happening again?",
    "answer": "[weather_checking OR weather_checking]"
  },
  {
    "question": "Is the weather checking happening twice, and are there ticket availability?",
    "answer": "[[weather_checking OR weather_checking] AND ticket_availability]"
  },
  {
    "question": "Is there event booking or ticket availability?",
    "answer": "[event_booking OR ticket_availability]"
  },
  {
    "question": "Should I check the weather or should I check the weather again?",
    "answer": "ONEOF[weather_checking; weather_checking]"
  },
  {
    "question": "Should I recommend parking spots and book an event?",
    "answer": "[parking_recommendation AND event_booking]"
  },
  {
    "question": "Should I check both the weather and recommend parking spots or look for ticket availability?",
    "answer": "[[weather_checking AND parking_recommendation] OR ticket_availability]"
  },
  {
    "question": "Is there event booking or is there ticket availability and weather checking?",
    "answer": "[event_booking OR [ticket_availability AND weather_checking]]"
  },
  {
    "question": "Should I look for ticket availability and then book an event?",
    "answer": "SEQ[ticket_availability; event_booking]"
  },
  {
    "question": "Should I look for ticket availability and recommend parking spots?",
    "answer": "[ticket_availability AND parking_recommendation]"
  },
  {
    "question": "Should I recommend parking spots or book an event?",
    "answer": "[parking_recommendation OR event_booking]"
  },
  {
    "question": "Is there event booking or is there event booking again and ticket availability?",
    "answer": "[[event_booking OR event_booking] AND ticket_availability]"
  },
  {
    "question": "Book an event and recommend parking spots.",
    "answer": "SEQ[event_booking; parking_recommendation]"
  },
  {
    "question": "Should I recommend parking spots or book an event?",
    "answer": "ONEOF[parking_recommendation; event_booking]"
  },
  {
    "question": "Is there event booking and should I recommend parking spots?",
    "answer": "[event_booking AND parking_recommendation]"
  },
  {
    "question": "Is there event booking and weather checking?",
    "answer": "[event_booking AND weather_checking]"
  },
  {
    "question": "Is there ticket availability and weather checking?",
    "answer": "[ticket_availability AND weather_checking]"
  },
  {
    "question": "Should I check the weather or is there event booking?",
    "answer": "[weather_checking OR event_booking]"
  },
  {
    "question": "Is there event booking and is there event booking again or is there ticket availability?",
    "answer": "[event_booking AND [event_booking OR ticket_availability]]"
  },
  {
    "question": "Is there ticket availability and is there ticket availability again?",
    "answer": "[ticket_availability AND ticket_availability]"
  },
  {
    "question": "Should I recommend parking spots or should I recommend parking spots again?",
    "answer": "[parking_recommendation OR parking_recommendation]"
  },
  {
    "question": "Is there weather checking or is there ticket availability?",
    "answer": "[weather_checking OR ticket_availability]"
  },
  {
    "question": "Is there ticket availability or is there event booking?",
    "answer": "[ticket_availability OR event_booking]"
  },
  {
    "question": "Are there two weather checking occurrences?",
    "answer": "[weather_checking AND weather_checking]"
  },
  {
    "question": "Is there weather checking and is there ticket availability?",
    "answer": "[weather_checking AND ticket_availability]"
  },
  {
    "question": "Is there parking recommendation or is there weather checking?",
    "answer": "[parking_recommendation OR weather_checking]"
  },
  {
    "question": "Is there event booking or is there parking recommendation?",
    "answer": "[event_booking OR parking_recommendation]"
  },
  {
    "question": "Is there parking recommendation and is there ticket availability?",
    "answer": "[parking_recommendation AND ticket_availability]"
  },
  {
    "question": "Is there ticket availability or is there parking recommendation?",
    "answer": "[ticket_availability OR parking_recommendation]"
  },
  {
    "question": "Is there ticket availability or is there ticket availability again?",
    "answer": "[ticket_availability OR ticket_availability]"
  },
  {
    "question": "Is there weather checking and is there event booking?",
    "answer": "[weather_checking AND event_booking]"
  },
  {
    "question": "Is there ticket availability and is there event booking?",
    "answer": "[ticket_availability AND event_booking]"
  },
  {
    "question": "Is there weather checking and is there event booking or is there event booking again?",
    "answer": "[weather_checking AND [event_booking OR event_booking]]"
  },
  {
    "question": "Is there event booking and is there event booking again?",
    "answer": "[event_booking AND event_booking]"
  },
  {
    "question": "Is there event booking or is there weather checking?",
    "answer": "[event_booking OR weather_checking]"
  },
  {
    "question": "Is there ticket availability twice or is there ticket availability?",
    "answer": "[[ticket_availability AND ticket_availability] OR ticket_availability]"
  },
  {
    "question": "Is there parking recommendation and is there weather checking?",
    "answer": "[parking_recommendation AND weather_checking]"
  },
  {
    "question": "Is there ticket availability and is there parking recommendation or is there parking recommendation?",
    "answer": "[[ticket_availability AND parking_recommendation] OR parking_recommendation]"
  },
  {
    "question": "Is there event booking and is there ticket availability?",
    "answer": "[event_booking AND ticket_availability]"
  },
  {
    "question": "Is there event booking or is there event booking and parking recommendation?",
    "answer": "[event_booking OR [event_booking AND parking_recommendation]]"
  }
  {
    "question": "Is there ticket availability and is there parking recommendation or is there weather checking?",
    "answer": "[ticket_availability AND [parking_recommendation OR weather_checking]]"
  },
  {
    "question": "Is there event booking or is there weather checking and event booking again?",
    "answer": "[event_booking OR [weather_checking AND event_booking]]"
  },
  {
    "question": "Is there parking recommendation or is there event booking and weather checking?",
    "answer": "[parking_recommendation OR [event_booking AND weather_checking]]"
  },
  {
    "question": "Is there weather checking and ticket availability or is there parking recommendation?",
    "answer": "[[weather_checking AND ticket_availability] OR parking_recommendation]"
  },
  {
    "question": "Is there weather checking or is there parking recommendation and event booking?",
    "answer": "[weather_checking OR [parking_recommendation AND event_booking]]"
  },
  {
    "question": "Is there event booking or is there weather checking and ticket availability?",
    "answer": "[event_booking OR [weather_checking AND ticket_availability]]"
  },
  {
    "question": "Is there ticket availability and event booking or is there ticket availability again?",
    "answer": "[[ticket_availability AND event_booking] OR ticket_availability]"
  },
  {
    "question": "Is there event booking again or is there weather checking twice?",
    "answer": "[[event_booking AND event_booking] OR weather_checking]"
  },
  {
    "question": "Is there ticket availability and should I check for parking recommendation or book an event?",
    "answer": "[ticket_availability AND [parking_recommendation OR event_booking]]"
  },
  {
    "question": "Is there weather checking and ticket availability or is there event booking?",
    "answer": "[[weather_checking AND ticket_availability] OR event_booking]"
  },
  {
    "question": "Is there weather checking or is there parking recommendation and event booking?",
    "answer": "[weather_checking OR [ticket_availability AND parking_recommendation]]"
  },
  {
    "question": "Is there ticket availability or is there parking recommendation and event booking?",
    "answer": "[[ticket_availability OR parking_recommendation] AND event_booking]"
  },
  {
    "question": "Is there event booking or is there event booking again and parking recommendation?",
    "answer": "[[event_booking OR event_booking] AND parking_recommendation]"
  },
  {
    "question": "Is there parking recommendation and ticket availability or is there event booking?",
    "answer": "[[parking_recommendation AND ticket_availability] OR event_booking]"
  },
  {
    "question": "Is there parking recommendation and should I check the weather or book an event?",
    "answer": "[parking_recommendation AND [weather_checking OR event_booking]]"
  },
  {
    "question": "Is there parking recommendation or is there parking recommendation twice?",
    "answer": "[parking_recommendation OR [parking_recommendation AND parking_recommendation]]"
  },
  {
    "question": "Is there weather checking twice or is there parking recommendation?",
    "answer": "[[weather_checking AND weather_checking] OR parking_recommendation]"
  },
  {
    "question": "Is there weather checking and should I check for ticket availability or ticket availability again?",
    "answer": "[weather_checking AND [ticket_availability OR ticket_availability]]"
  },
  {
    "question": "Is there ticket availability and weather checking or is there event booking?",
    "answer": "[[ticket_availability AND weather_checking] OR event_booking]"
  },
  {
    "question": "Is there event booking or is there weather checking and parking recommendation?",
    "answer": "[event_booking OR [weather_checking AND parking_recommendation]]"
  }
  {
    "question": "Is there event booking or is there weather checking and parking recommendation?",
    "answer": "[event_booking OR [weather_checking AND parking_recommendation]]"
  },
  {
    "question": "Is there event booking or is there parking recommendation and event booking?",
    "answer": "[[event_booking OR parking_recommendation] AND event_booking]"
  },
  {
    "question": "Is there event booking or is there parking recommendation and ticket availability?",
    "answer": "[event_booking OR [parking_recommendation AND ticket_availability]]"
  },
  {
    "question": "Is there weather checking and ticket availability or is there ticket availability again?",
    "answer": "[[weather_checking AND ticket_availability] OR ticket_availability]"
  },
  {
    "question": "Is there weather checking and should I check the weather or should I check the weather again?",
    "answer": "[weather_checking AND [weather_checking OR weather_checking]]"
  },
  {
    "question": "Is there weather checking or is there weather checking and should I check the weather again?",
    "answer": "[weather_checking OR [weather_checking AND weather_checking]]"
  },
  {
    "question": "Is there event booking or is there event booking again and event booking?",
    "answer": "[[event_booking OR event_booking] AND event_booking]"
  },
  {
    "question": "Is there parking recommendation or is there weather checking twice?",
    "answer": "[parking_recommendation OR [weather_checking AND weather_checking]]"
  },
  {
    "question": "Is there event booking and should I recommend parking spots or book an event?",
    "answer": "[event_booking AND [parking_recommendation OR event_booking]]"
  },
  {
    "question": "Is there parking recommendation and should I check the weather or should I recommend parking spots?",
    "answer": "[parking_recommendation AND [weather_checking OR parking_recommendation]]"
  },
  {
    "question": "Is there ticket availability or should I check the weather and event booking?",
    "answer": "[[ticket_availability OR weather_checking] AND event_booking]"
  },
  {
    "question": "Is there parking recommendation and event booking or is there event booking again?",
    "answer": "[[parking_recommendation AND event_booking] OR event_booking]"
  },
  {
    "question": "Is there parking recommendation or is there parking recommendation twice and ticket availability?",
    "answer": "[[parking_recommendation OR parking_recommendation] AND ticket_availability]"
  },
  {
    "question": "Is there ticket availability and should I check for ticket availability or should I check for ticket availability again?",
    "answer": "[ticket_availability AND [ticket_availability OR ticket_availability]]"
  },
  {
    "question": "Is there ticket availability or should I check the weather and event booking?",
    "answer": "[ticket_availability OR [weather_checking AND event_booking]]"
  },
  {
    "question": "Is there weather checking or is there event booking and event booking again?",
    "answer": "[weather_checking OR [event_booking AND event_booking]]"
  },
  {
    "question": "Is there parking recommendation and should I check for event booking or should I check for ticket availability?",
    "answer": "[parking_recommendation AND [event_booking OR ticket_availability]]"
  },
  {
    "question": "Is there ticket availability and should I check for event booking or should I check for ticket availability again?",
    "answer": "[ticket_availability AND [event_booking OR ticket_availability]]"
  },
  {
    "question": "Is there weather checking or is there parking recommendation twice?",
    "answer": "[weather_checking OR [parking_recommendation AND parking_recommendation]]"
  },
  {
    "question": "Is there event booking or is there ticket availability and parking recommendation?",
    "answer": "[[event_booking OR ticket_availability] AND parking_recommendation]"
  },
  {
    "question": "Is there parking recommendation and should I recommend parking spots or should I book an event?",
    "answer": "[parking_recommendation AND [parking_recommendation OR event_booking]]"
  }
  {
    "question": "Is there parking recommendation and should I recommend parking spots or should I book an event?",
    "answer": "[parking_recommendation AND [parking_recommendation OR event_booking]]"
  },
  {
    "question": "Is there parking recommendation or is there parking recommendation and event booking?",
    "answer": "[parking_recommendation OR [parking_recommendation AND event_booking]]"
  },
  {
    "question": "Is there parking recommendation or is there weather checking, and is there ticket availability?",
    "answer": "[[parking_recommendation OR weather_checking] AND ticket_availability]"
  },
  {
    "question": "Is there ticket availability and should I check for event booking or should I recommend parking spots?",
    "answer": "[ticket_availability AND [event_booking OR parking_recommendation]]"
  },
  {
    "question": "Is there ticket availability and event booking or is there parking recommendation?",
    "answer": "[[ticket_availability AND event_booking] OR parking_recommendation]"
  },
  {
    "question": "Is there parking recommendation or is there ticket availability and parking recommendation?",
    "answer": "[parking_recommendation OR [ticket_availability AND parking_recommendation]]"
  },
  {
    "question": "Is there weather checking and should I check for ticket availability or recommend parking spots?",
    "answer": "[weather_checking AND [ticket_availability OR parking_recommendation]]"
  },
  {
    "question": "Is there event booking and ticket availability or is there parking recommendation?",
    "answer": "[[event_booking AND ticket_availability] OR parking_recommendation]"
  },
  {
    "question": "Is there event booking or is there weather checking, and is there parking recommendation?",
    "answer": "[[event_booking OR weather_checking] AND parking_recommendation]"
  },
  {
    "question": "Is there weather checking and parking recommendation, or is there weather checking again?",
    "answer": "[[weather_checking AND parking_recommendation] OR weather_checking]"
  },
  {
    "question": "Is there event booking and should I check for ticket availability or should I check for event booking again?",
    "answer": "[event_booking AND [ticket_availability OR event_booking]]"
  },
  {
    "question": "Is there weather checking or is there ticket availability, and is there weather checking?",
    "answer": "[weather_checking OR [ticket_availability AND weather_checking]]"
  },
  {
    "question": "Is there event booking and should I check for weather checking or should I check for ticket availability?",
    "answer": "[event_booking AND [weather_checking OR ticket_availability]]"
  },
  {
    "question": "Is there parking recommendation or parking recommendation twice, and is there weather checking?",
    "answer": "[[parking_recommendation OR parking_recommendation] AND weather_checking]"
  },
  {
    "question": "Is there weather checking or ticket availability, and is there event booking?",
    "answer": "[[weather_checking OR ticket_availability] AND event_booking]"
  },
  {
    "question": "Is there parking recommendation and ticket availability, or is there weather checking?",
    "answer": "[[parking_recommendation AND ticket_availability] OR weather_checking]"
  },
  {
    "question": "Is there parking recommendation and should I check for ticket availability, or should I check the weather?",
    "answer": "[parking_recommendation AND [ticket_availability OR weather_checking]]"
  },
  {
    "question": "Is there event booking or is there parking recommendation, and is there weather checking?",
    "answer": "[[event_booking OR parking_recommendation] AND weather_checking]"
  },
  {
    "question": "Is there ticket availability, or is there ticket availability twice, and is there parking recommendation?",
    "answer": "[ticket_availability OR [ticket_availability AND parking_recommendation]]"
  },
  {
    "question": "Is there event booking or is there event booking and event booking?",
    "answer": "[[event_booking OR event_booking] AND event_booking]"
  },
  {
    "question": "Is there parking recommendation or is there event booking, and is there weather checking?",
    "answer": "[[parking_recommendation OR event_booking] AND weather_checking]"
  }
  {
    "question": "Is there weather checking or should I check for event booking and parking recommendation?",
    "answer": "[[weather_checking OR event_booking] AND parking_recommendation]"
  },
  {
    "question": "Is there parking recommendation and should I check for weather checking or should I check for ticket availability?",
    "answer": "[parking_recommendation AND [weather_checking OR ticket_availability]]"
  },
  {
    "question": "Is there weather checking or should I check for event booking and weather checking?",
    "answer": "[weather_checking OR [event_booking AND weather_checking]]"
  },
  {
    "question": "Is there parking recommendation and should I recommend parking spots, or should I check for ticket availability?",
    "answer": "[parking_recommendation AND [parking_recommendation OR ticket_availability]]"
  },
  {
    "question": "Is there ticket availability and should I check for event booking or should I check the weather?",
    "answer": "[ticket_availability AND [event_booking OR weather_checking]]"
  },
  {
    "question": "Is there weather checking and should I check the weather or should I check for ticket availability?",
    "answer": "[weather_checking AND [weather_checking OR ticket_availability]]"
  },
  {
    "question": "Is there weather checking or should I check for event booking and should I check for weather checking again?",
    "answer": "[[weather_checking OR event_booking] AND event_booking]"
  },
  {
    "question": "Is there ticket availability or should I check for weather checking and should I check the weather again?",
    "answer": "[[ticket_availability OR weather_checking] AND weather_checking]"
  },
  {
    "question": "Is there weather checking and should I check for event booking or should I check the weather again?",
    "answer": "[weather_checking AND [event_booking OR weather_checking]]"
  },
  {
    "question": "Is there parking recommendation or should I check for ticket availability and should I check for ticket availability again?",
    "answer": "[[parking_recommendation OR ticket_availability] AND ticket_availability]"
  },
  {
    "question": "Is there ticket availability or should I check the weather and should I check the weather again?",
    "answer": "[ticket_availability OR [weather_checking AND weather_checking]]"
  },
  {
    "question": "Is there ticket availability and should I check for event booking or should I check for event booking again?",
    "answer": "[ticket_availability AND [event_booking OR event_booking]]"
  },
  {
    "question": "Is there weather checking and should I check the weather twice, or should I check for event booking?",
    "answer": "[[weather_checking AND weather_checking] OR event_booking]"
  },
  {
    "question": "Is there parking recommendation and should I check for ticket availability, or should I check for ticket availability again?",
    "answer": "[[parking_recommendation AND ticket_availability] OR ticket_availability]"
  },
  {
    "question": "Is there ticket availability or should I check for event booking and should I check the weather?",
    "answer": "[[ticket_availability OR event_booking] AND weather_checking]"
  },
  {
    "question": "Is there weather checking or should I check the weather twice, and is there weather checking?",
    "answer": "[[weather_checking OR weather_checking] AND weather_checking]"
  },
  {
    "question": "Is there ticket availability and should I check for parking recommendation or should I check for parking recommendation again?",
    "answer": "[ticket_availability AND [parking_recommendation OR parking_recommendation]]"
  },
  {
    "question": "Is there parking recommendation and should I check for weather checking or should I check the weather twice?",
    "answer": "[parking_recommendation AND [weather_checking OR weather_checking]]"
  },
  {
    "question": "Is there parking recommendation and should I check for event booking or should I check the weather?",
    "answer": "[parking_recommendation AND [event_booking OR weather_checking]]"
  },
  {
    "question": "Is there parking recommendation or should I check for ticket availability and should I check the weather?",
    "answer": "[parking_recommendation OR [ticket_availability AND weather_checking]]"
  },
  {
    "question": "Is there ticket availability and should I check for event booking or should I check the weather?",
    "answer": "[[ticket_availability AND event_booking] OR weather_checking]"
  }
  {
    "question": "Is there parking recommendation or should I check for weather checking and should I check the weather again?",
    "answer": "[parking_recommendation OR [weather_checking AND ticket_availability]]"
  },
  {
    "question": "Is there event booking and should I check for ticket availability or should I check for parking recommendation?",
    "answer": "[event_booking AND [ticket_availability OR parking_recommendation]]"
  },
  {
    "question": "Is there event booking and should I check for event booking or should I check for event booking?",
    "answer": "[event_booking AND [event_booking OR event_booking]]"
  },
  {
    "question": "Is there ticket availability and should I check for weather checking or should I check the weather twice?",
    "answer": "[ticket_availability AND [weather_checking OR weather_checking]]"
  },
  {
    "question": "Is there weather checking or should I check for event booking and should I check for ticket availability?",
    "answer": "[weather_checking OR [event_booking AND ticket_availability]]"
  },
  {
    "question": "Is there parking recommendation or should I check for weather checking and should I check for event booking?",
    "answer": "[parking_recommendation OR [weather_checking AND event_booking]]"
  },
  {
    "question": "Is there ticket availability or event booking, and should I check for parking recommendation?",
    "answer": "[[ticket_availability OR event_booking] AND parking_recommendation]"
  },
  {
    "question": "Is there weather checking and should I check for event booking or should I check for ticket availability?",
    "answer": "[weather_checking AND [event_booking OR ticket_availability]]"
  },
  {
    "question": "Is there event booking or should I check for parking recommendation and should I check for weather checking?",
    "answer": "[event_booking OR [parking_recommendation AND weather_checking]]"
  },
  {
    "question": "Is there event booking and ticket availability, or should I check for event booking?",
    "answer": "[[event_booking AND ticket_availability] OR event_booking]"
  },
  {
    "question": "Is there parking recommendation or ticket availability, and should I check for parking recommendation again?",
    "answer": "[[parking_recommendation OR ticket_availability] AND parking_recommendation]"
  },
  {
    "question": "Is there parking recommendation and should I check for parking recommendation or should I check for weather checking?",
    "answer": "[parking_recommendation AND [parking_recommendation OR weather_checking]]"
  },
  {
    "question": "Is there ticket availability and parking recommendation, or should I check for weather checking?",
    "answer": "[[ticket_availability AND parking_recommendation] OR weather_checking]"
  },
  {
    "question": "Is there event booking and weather checking, or should I check the weather again?",
    "answer": "[[event_booking AND weather_checking] OR weather_checking]"
  },
  {
    "question": "Is there event booking or weather checking, and should I check for event booking?",
    "answer": "[[event_booking OR weather_checking] AND event_booking]"
  },
  {
    "question": "Is there ticket availability and should I check for ticket availability or should I check for parking recommendation?",
    "answer": "[ticket_availability AND [ticket_availability OR parking_recommendation]]"
  },
  {
    "question": "Is there weather checking or parking recommendation, and should I check for ticket availability?",
    "answer": "[[weather_checking OR parking_recommendation] AND ticket_availability]"
  },
  {
    "question": "Is there weather checking and parking recommendation, or should I check for event booking?",
    "answer": "[[weather_checking AND parking_recommendation] OR event_booking]"
  },
  {
    "question": "Is there weather checking and should I check the weather or should I check for event booking?",
    "answer": "[weather_checking AND [weather_checking OR event_booking]]"
  },
  {
    "question": "Is there ticket availability twice, or should I check the weather?",
    "answer": "[[ticket_availability AND ticket_availability] OR weather_checking]"
  },
  {
    "question": "Is there parking recommendation and should I check for ticket availability or event booking?",
    "answer": "[parking_recommendation AND [ticket_availability OR event_booking]]"
  },
  {
    "question": "Is there ticket availability and parking recommendation, or should I check for ticket availability?",
    "answer": "[[ticket_availability AND parking_recommendation] OR ticket_availability]"
  },
  {
    "question": "Is there parking recommendation and weather checking, or should I check the weather again?",
    "answer": "[[parking_recommendation AND weather_checking] OR weather_checking]"
  },
  {
    "question": "Is there parking recommendation or event booking, and should I check for event booking?",
    "answer": "[[parking_recommendation OR event_booking] AND event_booking]"
}
  
]